
{
  "ID": 141,
  "Name": "Twilight Glacier",
  "Resource Location": "twilightforest:twilight_glacier",
  "Class": "twilightforest.biomes.TFBiomeGlacier",
  "Root Height": 0.1,
  "Height Variation": 0.2,
  "Top Block": "minecraft:grass[snowy\u003dfalse]",
  "Filler Block": "minecraft:dirt[snowy\u003dfalse,variant\u003ddirt]",
  "Ocean Top Block": "Disabled. Activate in BiomeTweakerCore.",
  "Ocean Filler Block": "Disabled. Activate in BiomeTweakerCore.",
  "Actual Filler Blocks": "Disabled. Activate in BiomeTweakerCore.",
  "Grass Color": "Disabled. Activate in BiomeTweakerCore.",
  "Foliage Color": "Disabled. Activate in BiomeTweakerCore.",
  "Water Color": "4159204",
  "Temperature": 0.0,
  "Humidity": 0.1,
  "Water Tint": 4159204,
  "Enable Rain": true,
  "Enable Snow": true,
  "Dictionary Types": [
    "SNOWY",
    "WASTELAND",
    "TWILIGHT",
    "COLD"
  ],
  "BiomeManager Entries": {},
  "Spawnable Creatures": [
    {
      "Entity Class": "twilightforest.entity.passive.EntityTFPenguin",
      "Weight": 10,
      "Min Group Count": 4,
      "Max Group Count": 4
    }
  ],
  "Spawnable Monsters": [
    {
      "Entity Class": "electroblob.wizardry.entity.living.EntityIceWraith",
      "Weight": 3,
      "Min Group Count": 1,
      "Max Group Count": 1
    },
    {
      "Entity Class": "electroblob.wizardry.entity.living.EntityLightningWraith",
      "Weight": 1,
      "Min Group Count": 1,
      "Max Group Count": 1
    },
    {
      "Entity Class": "electroblob.wizardry.entity.living.EntityEvilWizard",
      "Weight": 0,
      "Min Group Count": 1,
      "Max Group Count": 1
    },
    {
      "Entity Class": "com.Fishmod.mod_LavaCow.entities.EntityUndertaker",
      "Weight": 8,
      "Min Group Count": 1,
      "Max Group Count": 1
    },
    {
      "Entity Class": "com.windanesz.ancientspellcraft.entity.living.EntityVoidCreeper",
      "Weight": 0,
      "Min Group Count": 1,
      "Max Group Count": 1
    },
    {
      "Entity Class": "com.windanesz.ancientspellcraft.entity.living.EntitySkeletonMage",
      "Weight": 3,
      "Min Group Count": 1,
      "Max Group Count": 3
    },
    {
      "Entity Class": "com.windanesz.ancientspellcraft.entity.living.EntityEvilClassWizard",
      "Weight": 2,
      "Min Group Count": 1,
      "Max Group Count": 1
    }
  ],
  "Spawnable Water Creatures": [],
  "Spawnable Cave Creatures": [
    {
      "Entity Class": "net.minecraft.entity.passive.EntityBat",
      "Weight": 10,
      "Min Group Count": 8,
      "Max Group Count": 8
    },
    {
      "Entity Class": "twilightforest.entity.passive.EntityTFMobileFirefly",
      "Weight": 10,
      "Min Group Count": 8,
      "Max Group Count": 8
    }
  ],
  "Spawn Biome": false,
  "Tweaked": false,
  "BOP Generators": {
    "FLOWERS Generators": [
      {
        "ID": "flora",
        "Name": "glowshrooms"
      },
      {
        "ID": "flora",
        "Name": "miners_delight"
      }
    ]
  },
  "BOP Owner": "OTHER",
  "BOP Weight Map": {},
  "BOP Climate Weights": {},
  "BOP Island Weight": 0
}